[
    {
        "title": "Falar com Emissao de notas",
        "start": "2026-04-29T17:00:00Z",
        "url": "https://calendly.com/contabilizei-lives/emissao-notas-fiscais/2026-04-29T17:00:00+00:00"
    },
    {
        "title": "Falar com Emissao de notas",
        "start": "2026-04-29T18:00:00Z",
        "url": "https://calendly.com/contabilizei-lives/emissao-notas-fiscais/2026-04-29T18:00:00+00:00"
    },
    {
        "title": "Falar com Emissao de notas",
        "start": "2026-04-29T21:00:00Z",
        "url": "https://calendly.com/contabilizei-lives/emissao-notas-fiscais/2026-04-29T21:00:00+00:00"
    },
    {
        "title": "Falar com Emissao de notas",
        "start": "2026-04-30T12:30:00Z",
        "url": "https://calendly.com/contabilizei-lives/emissao-notas-fiscais/2026-04-30T12:30:00+00:00"
    },
    {
        "title": "Falar com Emissao de notas",
        "start": "2026-04-30T14:00:00Z",
        "url": "https://calendly.com/contabilizei-lives/emissao-notas-fiscais/2026-04-30T14:00:00+00:00"
    },
    {
        "title": "Falar com Emissao de notas",
        "start": "2026-04-30T18:00:00Z",
        "url": "https://calendly.com/contabilizei-lives/emissao-notas-fiscais/2026-04-30T18:00:00+00:00"
    },
    {
        "title": "Falar com Emissao de notas",
        "start": "2026-04-30T22:00:00Z",
        "url": "https://calendly.com/contabilizei-lives/emissao-notas-fiscais/2026-04-30T22:00:00+00:00"
    }
]